_btclib_libsecp256k1.cpython-311-x86_64-linux-musl.so
btclib_libsecp256k1-0.4.0.dist-info/WHEEL
btclib_libsecp256k1-0.4.0.dist-info/METADATA
btclib_libsecp256k1-0.4.0.dist-info/RECORD
btclib_libsecp256k1-0.4.0.dist-info/licenses/LICENSE
btclib_libsecp256k1/py.typed
btclib_libsecp256k1/__init__.py
btclib_libsecp256k1/ssa.py
btclib_libsecp256k1/mult.py
btclib_libsecp256k1/dsa.py
