Metadata-Version: 2.1
Name: btclib_libsecp256k1
Version: 0.4.0
Summary: Simple python bindings to libsecp256k1
Project-URL: homepage, https://btclib.org
Project-URL: documentation, https://btclib.readthedocs.io/
Project-URL: repository, https://github.com/btclib-org/btclib_libsecp256k1
Project-URL: download, https://github.com/btclib-org/btclib_libsecp256k1/releases
Project-URL: changelog, https://github.com/btclib-org/btclib_libsecp256k1/HISTORY.md
Project-URL: issues, https://github.com/btclib-org/btclib_libsecp256k1/issues
Project-URL: pull_requests, https://github.com/btclib-org/btclib_libsecp256k1/pulls
Author-email: Giacomo Caironi <giacomo.caironi@gmail.com>
License: MIT
License-File: LICENSE
Keywords: bitcoin,libsecp256k1
Classifier: Development Status :: 4 - Beta
Classifier: Intended Audience :: Developers
Classifier: Intended Audience :: Education
Classifier: License :: OSI Approved :: MIT License
Classifier: Natural Language :: English
Classifier: Operating System :: OS Independent
Classifier: Programming Language :: Python :: 3 :: Only
Classifier: Programming Language :: Python :: 3.7
Classifier: Programming Language :: Python :: 3.8
Classifier: Programming Language :: Python :: 3.9
Classifier: Programming Language :: Python :: 3.10
Classifier: Programming Language :: Python :: 3.11
Classifier: Programming Language :: Python :: 3.12
Classifier: Programming Language :: Python :: Implementation :: CPython
Classifier: Programming Language :: Python :: Implementation :: PyPy
Classifier: Topic :: Scientific/Engineering
Classifier: Topic :: Security :: Cryptography
Classifier: Topic :: Software Development :: Libraries :: Python Modules
Requires-Python: >=3.7
Requires-Dist: cffi>=1.0.0
